geokde/__init__.py
geokde/_kernels.py
geokde/_utils.py
geokde/geokde.py
geokde-0.1.2.dist-info/LICENSE
geokde-0.1.2.dist-info/METADATA
geokde-0.1.2.dist-info/WHEEL
geokde-0.1.2.dist-info/RECORD
