Metadata-Version: 2.1
Name: geokde
Version: 0.1.2
Summary: Package for geospatial kernel density estimation (KDE).
Author: Duncan Martyn
Author-email: duncan.martyn@hotmail.co.uk
Requires-Python: >=3.10,<4.0
Classifier: Programming Language :: Python :: 3
Classifier: Programming Language :: Python :: 3.10
Classifier: Programming Language :: Python :: 3.11
Classifier: Programming Language :: Python :: 3.12
Requires-Dist: geopandas (>=0.14.3,<0.15.0)
